README.txt
setup.py
luo/TicToc.py
luo/__init__.py
luo/test.py
luo.egg-info/PKG-INFO
luo.egg-info/SOURCES.txt
luo.egg-info/dependency_links.txt
luo.egg-info/top_level.txt
luo.egg-info/zip-safe