Metadata-Version: 1.1
Name: luo
Version: 0.0.3
Summary: tools for luo
Home-page: https://github.com/guruL/luo
Author: yucheng
Author-email: yuchengluo@outlook.com
License: MIT
Keywords: tools
Platform: UNKNOWN
Classifier: License :: OSI Approved :: MIT License
Classifier: Programming Language :: Python
Classifier: Operating System :: OS Independent
Classifier: Topic :: Scientific/Engineering :: Astronomy
Classifier: Topic :: Scientific/Engineering :: GIS
Classifier: Topic :: Scientific/Engineering :: Mathematics
Classifier: Intended Audience :: Science/Research
Classifier: Intended Audience :: Developers
Classifier: Intended Audience :: Information Technology
